{"fr":60,"v":"5.9.6","ip":0,"op":299,"w":183,"h":187,"nm":"Frame 1","ddd":0,"markers":[],"assets":[{"nm":"Frame 1","fr":60,"id":"mbmahqp150whrhwb","layers":[{"ty":3,"ddd":0,"ind":5,"hd":false,"nm":"Frame 1 - Null","sr":1,"ks":{"a":{"a":0,"k":[0,0]},"o":{"a":0,"k":100},"p":{"a":0,"k":[0,0]},"r":{"a":0,"k":0},"s":{"a":0,"k":[100,100]},"sk":{"a":0,"k":0},"sa":{"a":0,"k":0}},"ao":0,"ip":0,"op":300,"st":0,"bm":0},{"ty":3,"ddd":0,"ind":6,"hd":false,"nm":"Line 4 - Null","sr":1,"parent":5,"ks":{"a":{"a":0,"k":[0,0]},"o":{"a":0,"k":100},"p":{"a":0,"k":[24,150]},"r":{"a":0,"k":0},"s":{"a":0,"k":[100,100]},"sk":{"a":0,"k":0},"sa":{"a":0,"k":0}},"ao":0,"ip":0,"op":300,"st":0,"bm":0},{"ddd":0,"ind":7,"hd":false,"nm":"Line 4 - Stroke","sr":1,"parent":6,"ks":{"a":{"a":0,"k":[0,0]},"p":{"a":0,"k":[0,0]},"s":{"a":0,"k":[100,100]},"sk":{"a":0,"k":0},"sa":{"a":0,"k":0},"r":{"a":0,"k":0},"o":{"a":0,"k":100}},"ao":0,"ip":0,"op":300,"st":0,"bm":0,"ty":4,"shapes":[{"ty":"gr","nm":"Group","hd":false,"np":3,"it":[{"ty":"sh","nm":"Path","hd":false,"ks":{"a":0,"k":{"c":false,"v":[[0,0],[139,0]],"i":[[0,0],[0,0]],"o":[[0,0],[0,0]]}}},{"ty":"st","c":{"a":0,"k":[0,0,0,1]},"o":{"a":0,"k":100},"w":{"a":0,"k":9},"lc":2,"lj":1,"ml":4,"bm":0,"nm":"Stroke","hd":false},{"ty":"tr","a":{"a":0,"k":[0,0]},"p":{"a":0,"k":[0,0]},"s":{"a":0,"k":[100,100]},"sk":{"a":0,"k":0},"sa":{"a":0,"k":0},"r":{"a":0,"k":0},"o":{"a":0,"k":100}}]},{"ty":"tm","s":{"a":0,"k":0},"e":{"a":1,"k":[{"t":0,"s":[0],"o":{"x":[0.5],"y":[0.35]},"i":{"x":[0.15],"y":[1]}},{"t":54.455999999999996,"s":[100]}]},"o":{"a":0,"k":0},"m":1},{"ty":"gr","nm":"Group","hd":false,"np":3,"it":[{"ty":"rc","nm":"Rectangle","hd":false,"p":{"a":0,"k":[74,4.5]},"s":{"a":0,"k":[296,18]},"r":{"a":0,"k":0}},{"ty":"fl","o":{"a":0,"k":0},"c":{"a":0,"k":[0,1,0,1]},"nm":"Fill","hd":false,"r":1},{"ty":"tr","a":{"a":0,"k":[0,0]},"p":{"a":0,"k":[0,0]},"s":{"a":0,"k":[100,100]},"sk":{"a":0,"k":0},"sa":{"a":0,"k":0},"r":{"a":0,"k":0},"o":{"a":0,"k":100}}]}]},{"ty":3,"ddd":0,"ind":8,"hd":false,"nm":"Line 3 - Null","sr":1,"parent":5,"ks":{"a":{"a":0,"k":[0,0]},"o":{"a":0,"k":100},"p":{"a":0,"k":[24.3032,17.944]},"r":{"a":0,"k":47.2258},"s":{"a":0,"k":[100,100]},"sk":{"a":0,"k":0},"sa":{"a":0,"k":0}},"ao":0,"ip":0,"op":300,"st":0,"bm":0},{"ddd":0,"ind":9,"hd":false,"nm":"Line 3 - Stroke","sr":1,"parent":8,"ks":{"a":{"a":0,"k":[0,0]},"p":{"a":0,"k":[0,0]},"s":{"a":0,"k":[100,100]},"sk":{"a":0,"k":0},"sa":{"a":0,"k":0},"r":{"a":0,"k":0},"o":{"a":0,"k":100}},"ao":0,"ip":0,"op":300,"st":0,"bm":0,"ty":4,"shapes":[{"ty":"gr","nm":"Group","hd":false,"np":3,"it":[{"ty":"sh","nm":"Path","hd":false,"ks":{"a":0,"k":{"c":false,"v":[[0,0],[200.2623,0]],"i":[[0,0],[0,0]],"o":[[0,0],[0,0]]}}},{"ty":"st","c":{"a":0,"k":[0,0,0,1]},"o":{"a":0,"k":100},"w":{"a":0,"k":9},"lc":2,"lj":1,"ml":4,"bm":0,"nm":"Stroke","hd":false},{"ty":"tr","a":{"a":0,"k":[0,0]},"p":{"a":0,"k":[0,0]},"s":{"a":0,"k":[100,100]},"sk":{"a":0,"k":0},"sa":{"a":0,"k":0},"r":{"a":0,"k":0},"o":{"a":0,"k":100}}]},{"ty":"tm","s":{"a":0,"k":0},"e":{"a":1,"k":[{"t":0,"s":[0],"o":{"x":[0.5],"y":[0.35]},"i":{"x":[0.15],"y":[1]}},{"t":54.455999999999996,"s":[100]}]},"o":{"a":0,"k":0},"m":1},{"ty":"gr","nm":"Group","hd":false,"np":3,"it":[{"ty":"rc","nm":"Rectangle","hd":false,"p":{"a":0,"k":[104.63115,4.5]},"s":{"a":0,"k":[418.5246,18]},"r":{"a":0,"k":0}},{"ty":"fl","o":{"a":0,"k":0},"c":{"a":0,"k":[0,1,0,1]},"nm":"Fill","hd":false,"r":1},{"ty":"tr","a":{"a":0,"k":[0,0]},"p":{"a":0,"k":[0,0]},"s":{"a":0,"k":[100,100]},"sk":{"a":0,"k":0},"sa":{"a":0,"k":0},"r":{"a":0,"k":0},"o":{"a":0,"k":100}}]}]},{"ty":4,"ddd":0,"ind":10,"hd":false,"nm":"Frame 1","sr":1,"parent":5,"ks":{"a":{"a":0,"k":[0,0]},"p":{"a":0,"k":[0,0]},"s":{"a":0,"k":[100,100]},"sk":{"a":0,"k":0},"sa":{"a":0,"k":0},"r":{"a":0,"k":0},"o":{"a":0,"k":100}},"ao":0,"ip":0,"op":300,"st":0,"bm":0,"shapes":[{"ty":"gr","nm":"Group","hd":false,"np":3,"it":[{"ty":"sh","nm":"Path","hd":false,"ks":{"a":0,"k":{"c":true,"v":[[0.01,0],[182.99,0],[183,0.01],[183,186.99],[182.99,187],[0.01,187],[0,186.99],[0,0.01],[0.01,0],[0.01,0]],"i":[[0,0],[0,0],[0,-0.0055],[0,0],[0.0055,0],[0,0],[0,0.0055],[0,0],[-0.0055,0],[0,0]],"o":[[0,0],[0.005519999999989977,0],[0,0],[0,0.005519999999989977],[0,0],[-0.00552,0],[0,0],[0,-0.00552],[0,0],[0,0]]}}},{"ty":"fl","o":{"a":0,"k":100},"c":{"a":0,"k":[1,1,1,1]},"nm":"Fill","hd":false,"r":1},{"ty":"tr","a":{"a":0,"k":[0,0]},"p":{"a":0,"k":[0,0]},"s":{"a":0,"k":[100,100]},"sk":{"a":0,"k":0},"sa":{"a":0,"k":0},"r":{"a":0,"k":0},"o":{"a":0,"k":100}}]}]}]}],"layers":[{"ty":3,"ddd":0,"ind":5,"hd":false,"nm":"Frame 1 - Null","sr":1,"ks":{"a":{"a":0,"k":[0,0]},"o":{"a":0,"k":100},"p":{"a":0,"k":[0,0]},"r":{"a":0,"k":0},"s":{"a":0,"k":[100,100]},"sk":{"a":0,"k":0},"sa":{"a":0,"k":0}},"ao":0,"ip":0,"op":300,"st":0,"bm":0},{"ddd":0,"ind":2,"ty":0,"nm":"Frame 1","refId":"mbmahqp150whrhwb","sr":1,"ks":{"a":{"a":0,"k":[0,0]},"p":{"a":0,"k":[0,0]},"s":{"a":0,"k":[100,100]},"sk":{"a":0,"k":0},"sa":{"a":0,"k":0},"r":{"a":0,"k":0},"o":{"a":0,"k":100}},"ao":0,"w":183,"h":187,"ip":0,"op":300,"st":0,"hd":false,"bm":0}],"meta":{"a":"","d":"","tc":"","g":"Aninix"}}